{
  "date": "2026-04-14",
  "scan_time": "17:15",
  "total_scanned": 2707,
  "buy": [
    {
      "code": "900100",
      "name": "애머릿지",
      "market": "KOSDAQ",
      "close": 608,
      "change": 10.95,
      "cloud_top": 596,
      "cloud_bot": 468,
      "volume": 22174416,
      "market_cap": 320,
      "volume_ratio": null,
      "ma5": null,
      "ma20": null,
      "ma60": null,
      "cloud_pos": null,
      "aligned": null
    },
    {
      "code": "347000",
      "name": "센코",
      "market": "KOSDAQ",
      "close": 2330,
      "change": 8.12,
      "cloud_top": 2295,
      "cloud_bot": 2253,
      "volume": 5600614,
      "market_cap": 880,
      "volume_ratio": null,
      "ma5": null,
      "ma20": null,
      "ma60": null,
      "cloud_pos": null,
      "aligned": null
    },
    {
      "code": "456010",
      "name": "아이씨티케이",
      "market": "KOSDAQ",
      "close": 17660,
      "change": 11.77,
      "cloud_top": 16190,
      "cloud_bot": 16060,
      "volume": 4799698,
      "market_cap": 2455,
      "volume_ratio": null,
      "ma5": null,
      "ma20": null,
      "ma60": null,
      "cloud_pos": null,
      "aligned": null
    },
    {
      "code": "434480",
      "name": "모니터랩",
      "market": "KOSDAQ",
      "close": 3970,
      "change": 17.11,
      "cloud_top": 3755,
      "cloud_bot": 3618,
      "volume": 4707781,
      "market_cap": 488,
      "volume_ratio": null,
      "ma5": null,
      "ma20": null,
      "ma60": null,
      "cloud_pos": null,
      "aligned": null
    },
    {
      "code": "004980",
      "name": "성신양회",
      "market": "KOSPI",
      "close": 12380,
      "change": 29.91,
      "cloud_top": 9795,
      "cloud_bot": 9682,
      "volume": 3889830,
      "market_cap": 3035,
      "volume_ratio": null,
      "ma5": null,
      "ma20": null,
      "ma60": null,
      "cloud_pos": null,
      "aligned": null
    },
    {
      "code": "048430",
      "name": "유라테크",
      "market": "KOSDAQ",
      "close": 8950,
      "change": 16.54,
      "cloud_top": 7935,
      "cloud_bot": 7912,
      "volume": 3538943,
      "market_cap": 1031,
      "volume_ratio": null,
      "ma5": null,
      "ma20": null,
      "ma60": null,
      "cloud_pos": null,
      "aligned": null
    },
    {
      "code": "052900",
      "name": "KX하이텍",
      "market": "KOSDAQ",
      "close": 1271,
      "change": 9.95,
      "cloud_top": 1258,
      "cloud_bot": 1238,
      "volume": 3513185,
      "market_cap": 883,
      "volume_ratio": null,
      "ma5": null,
      "ma20": null,
      "ma60": null,
      "cloud_pos": null,
      "aligned": null
    },
    {
      "code": "102120",
      "name": "어보브반도체",
      "market": "KOSDAQ",
      "close": 12160,
      "change": 8.96,
      "cloud_top": 12095,
      "cloud_bot": 12095,
      "volume": 3470004,
      "market_cap": 2162,
      "volume_ratio": null,
      "ma5": null,
      "ma20": null,
      "ma60": null,
      "cloud_pos": null,
      "aligned": null
    },
    {
      "code": "085670",
      "name": "뉴프렉스",
      "market": "KOSDAQ",
      "close": 6240,
      "change": 12.64,
      "cloud_top": 5835,
      "cloud_bot": 5717,
      "volume": 3230452,
      "market_cap": 1525,
      "volume_ratio": null,
      "ma5": null,
      "ma20": null,
      "ma60": null,
      "cloud_pos": null,
      "aligned": null
    },
    {
      "code": "465480",
      "name": "인스피언",
      "market": "KOSDAQ",
      "close": 5890,
      "change": 13.93,
      "cloud_top": 5475,
      "cloud_bot": 5267,
      "volume": 2882814,
      "market_cap": 597,
      "volume_ratio": null,
      "ma5": null,
      "ma20": null,
      "ma60": null,
      "cloud_pos": null,
      "aligned": null
    },
    {
      "code": "078890",
      "name": "가온그룹",
      "market": "KOSDAQ",
      "close": 7850,
      "change": 29.97,
      "cloud_top": 6830,
      "cloud_bot": 6340,
      "volume": 2734194,
      "market_cap": 1446,
      "volume_ratio": null,
      "ma5": null,
      "ma20": null,
      "ma60": null,
      "cloud_pos": null,
      "aligned": null
    },
    {
      "code": "003620",
      "name": "KG모빌리티",
      "market": "KOSPI",
      "close": 4040,
      "change": 6.32,
      "cloud_top": 3957,
      "cloud_bot": 3931,
      "volume": 2725023,
      "market_cap": 8175,
      "volume_ratio": null,
      "ma5": null,
      "ma20": null,
      "ma60": null,
      "cloud_pos": null,
      "aligned": null
    },
    {
      "code": "042940",
      "name": "상지건설",
      "market": "KOSDAQ",
      "close": 11190,
      "change": 5.57,
      "cloud_top": 10685,
      "cloud_bot": 9385,
      "volume": 2548758,
      "market_cap": 764,
      "volume_ratio": null,
      "ma5": null,
      "ma20": null,
      "ma60": null,
      "cloud_pos": null,
      "aligned": null
    },
    {
      "code": "317120",
      "name": "라닉스",
      "market": "KOSDAQ",
      "close": 2115,
      "change": 8.85,
      "cloud_top": 2091,
      "cloud_bot": 1986,
      "volume": 2138200,
      "market_cap": 322,
      "volume_ratio": null,
      "ma5": null,
      "ma20": null,
      "ma60": null,
      "cloud_pos": null,
      "aligned": null
    },
    {
      "code": "013580",
      "name": "계룡건설",
      "market": "KOSPI",
      "close": 30150,
      "change": 17.54,
      "cloud_top": 26137,
      "cloud_bot": 24825,
      "volume": 1915687,
      "market_cap": 2692,
      "volume_ratio": null,
      "ma5": null,
      "ma20": null,
      "ma60": null,
      "cloud_pos": null,
      "aligned": null
    },
    {
      "code": "274090",
      "name": "켄코아에어로스페이스",
      "market": "KOSDAQ",
      "close": 23900,
      "change": 11.16,
      "cloud_top": 22122,
      "cloud_bot": 20870,
      "volume": 1731720,
      "market_cap": 3279,
      "volume_ratio": null,
      "ma5": null,
      "ma20": null,
      "ma60": null,
      "cloud_pos": null,
      "aligned": null
    },
    {
      "code": "411080",
      "name": "샌즈랩",
      "market": "KOSDAQ",
      "close": 6930,
      "change": 8.45,
      "cloud_top": 6675,
      "cloud_bot": 6327,
      "volume": 1651962,
      "market_cap": 1058,
      "volume_ratio": null,
      "ma5": null,
      "ma20": null,
      "ma60": null,
      "cloud_pos": null,
      "aligned": null
    },
    {
      "code": "054920",
      "name": "한컴위드",
      "market": "KOSDAQ",
      "close": 5350,
      "change": 7.21,
      "cloud_top": 5320,
      "cloud_bot": 5097,
      "volume": 1240706,
      "market_cap": 1509,
      "volume_ratio": null,
      "ma5": null,
      "ma20": null,
      "ma60": null,
      "cloud_pos": null,
      "aligned": null
    },
    {
      "code": "025820",
      "name": "이구산업",
      "market": "KOSPI",
      "close": 5580,
      "change": 3.72,
      "cloud_top": 5567,
      "cloud_bot": 5452,
      "volume": 939683,
      "market_cap": 1866,
      "volume_ratio": null,
      "ma5": null,
      "ma20": null,
      "ma60": null,
      "cloud_pos": null,
      "aligned": null
    },
    {
      "code": "036200",
      "name": "유니셈",
      "market": "KOSDAQ",
      "close": 10600,
      "change": 8.05,
      "cloud_top": 10285,
      "cloud_bot": 10122,
      "volume": 927081,
      "market_cap": 3250,
      "volume_ratio": null,
      "ma5": null,
      "ma20": null,
      "ma60": null,
      "cloud_pos": null,
      "aligned": null
    },
    {
      "code": "007980",
      "name": "TP",
      "market": "KOSPI",
      "close": 2000,
      "change": 4.6,
      "cloud_top": 1947,
      "cloud_bot": 1947,
      "volume": 926508,
      "market_cap": 1023,
      "volume_ratio": null,
      "ma5": null,
      "ma20": null,
      "ma60": null,
      "cloud_pos": null,
      "aligned": null
    },
    {
      "code": "005940",
      "name": "NH투자증권",
      "market": "KOSPI",
      "close": 35200,
      "change": 3.99,
      "cloud_top": 33050,
      "cloud_bot": 31525,
      "volume": 874254,
      "market_cap": 125433,
      "volume_ratio": null,
      "ma5": null,
      "ma20": null,
      "ma60": null,
      "cloud_pos": null,
      "aligned": null
    },
    {
      "code": "045390",
      "name": "대아티아이",
      "market": "KOSDAQ",
      "close": 4470,
      "change": 2.76,
      "cloud_top": 4452,
      "cloud_bot": 4342,
      "volume": 790167,
      "market_cap": 3150,
      "volume_ratio": null,
      "ma5": null,
      "ma20": null,
      "ma60": null,
      "cloud_pos": null,
      "aligned": null
    },
    {
      "code": "430690",
      "name": "한싹",
      "market": "KOSDAQ",
      "close": 4690,
      "change": 29.92,
      "cloud_top": 4220,
      "cloud_bot": 3947,
      "volume": 726262,
      "market_cap": 510,
      "volume_ratio": null,
      "ma5": null,
      "ma20": null,
      "ma60": null,
      "cloud_pos": null,
      "aligned": null
    },
    {
      "code": "136480",
      "name": "하림",
      "market": "KOSDAQ",
      "close": 3240,
      "change": 1.89,
      "cloud_top": 3205,
      "cloud_bot": 3182,
      "volume": 724263,
      "market_cap": 3441,
      "volume_ratio": null,
      "ma5": null,
      "ma20": null,
      "ma60": null,
      "cloud_pos": null,
      "aligned": null
    },
    {
      "code": "129890",
      "name": "앱코",
      "market": "KOSDAQ",
      "close": 1098,
      "change": 3.88,
      "cloud_top": 1087,
      "cloud_bot": 930,
      "volume": 660151,
      "market_cap": 500,
      "volume_ratio": null,
      "ma5": null,
      "ma20": null,
      "ma60": null,
      "cloud_pos": null,
      "aligned": null
    },
    {
      "code": "050120",
      "name": "ES큐브",
      "market": "KOSDAQ",
      "close": 3180,
      "change": 22.31,
      "cloud_top": 2845,
      "cloud_bot": 2742,
      "volume": 654367,
      "market_cap": 431,
      "volume_ratio": null,
      "ma5": null,
      "ma20": null,
      "ma60": null,
      "cloud_pos": null,
      "aligned": null
    },
    {
      "code": "004985",
      "name": "성신양회우",
      "market": "KOSPI",
      "close": 13740,
      "change": 27.93,
      "cloud_top": 12450,
      "cloud_bot": 11052,
      "volume": 632760,
      "market_cap": 101,
      "volume_ratio": null,
      "ma5": null,
      "ma20": null,
      "ma60": null,
      "cloud_pos": null,
      "aligned": null
    },
    {
      "code": "223310",
      "name": "사토시홀딩스",
      "market": "KOSDAQ",
      "close": 1992,
      "change": 29.94,
      "cloud_top": 1952,
      "cloud_bot": 1651,
      "volume": 570811,
      "market_cap": 518,
      "volume_ratio": null,
      "ma5": null,
      "ma20": null,
      "ma60": null,
      "cloud_pos": null,
      "aligned": null
    },
    {
      "code": "211270",
      "name": "AP위성",
      "market": "KOSDAQ",
      "close": 17110,
      "change": 4.01,
      "cloud_top": 16860,
      "cloud_bot": 16640,
      "volume": 550613,
      "market_cap": 2580,
      "volume_ratio": null,
      "ma5": null,
      "ma20": null,
      "ma60": null,
      "cloud_pos": null,
      "aligned": null
    },
    {
      "code": "092870",
      "name": "엑시콘",
      "market": "KOSDAQ",
      "close": 30550,
      "change": 10.09,
      "cloud_top": 28337,
      "cloud_bot": 24250,
      "volume": 504188,
      "market_cap": 3987,
      "volume_ratio": null,
      "ma5": null,
      "ma20": null,
      "ma60": null,
      "cloud_pos": null,
      "aligned": null
    },
    {
      "code": "365330",
      "name": "에스와이스틸텍",
      "market": "KOSDAQ",
      "close": 3845,
      "change": 1.99,
      "cloud_top": 3817,
      "cloud_bot": 3641,
      "volume": 476920,
      "market_cap": 1929,
      "volume_ratio": null,
      "ma5": null,
      "ma20": null,
      "ma60": null,
      "cloud_pos": null,
      "aligned": null
    },
    {
      "code": "144960",
      "name": "뉴파워프라즈마",
      "market": "KOSDAQ",
      "close": 5740,
      "change": 3.24,
      "cloud_top": 5692,
      "cloud_bot": 5615,
      "volume": 467904,
      "market_cap": 2507,
      "volume_ratio": null,
      "ma5": null,
      "ma20": null,
      "ma60": null,
      "cloud_pos": null,
      "aligned": null
    },
    {
      "code": "092300",
      "name": "현우산업",
      "market": "KOSDAQ",
      "close": 3390,
      "change": 8.13,
      "cloud_top": 3350,
      "cloud_bot": 3350,
      "volume": 448417,
      "market_cap": 645,
      "volume_ratio": null,
      "ma5": null,
      "ma20": null,
      "ma60": null,
      "cloud_pos": null,
      "aligned": null
    },
    {
      "code": "489790",
      "name": "한화비전",
      "market": "KOSPI",
      "close": 76900,
      "change": 2.26,
      "cloud_top": 75425,
      "cloud_bot": 65025,
      "volume": 429289,
      "market_cap": 38825,
      "volume_ratio": null,
      "ma5": null,
      "ma20": null,
      "ma60": null,
      "cloud_pos": null,
      "aligned": null
    },
    {
      "code": "315640",
      "name": "딥노이드",
      "market": "KOSDAQ",
      "close": 3675,
      "change": 3.67,
      "cloud_top": 3512,
      "cloud_bot": 3435,
      "volume": 407792,
      "market_cap": 1079,
      "volume_ratio": null,
      "ma5": null,
      "ma20": null,
      "ma60": null,
      "cloud_pos": null,
      "aligned": null
    },
    {
      "code": "049800",
      "name": "우진플라임",
      "market": "KOSPI",
      "close": 2990,
      "change": 15.0,
      "cloud_top": 2863,
      "cloud_bot": 2775,
      "volume": 364785,
      "market_cap": 598,
      "volume_ratio": null,
      "ma5": null,
      "ma20": null,
      "ma60": null,
      "cloud_pos": null,
      "aligned": null
    },
    {
      "code": "071050",
      "name": "한국금융지주",
      "market": "KOSPI",
      "close": 257500,
      "change": 4.67,
      "cloud_top": 243325,
      "cloud_bot": 227350,
      "volume": 360375,
      "market_cap": 143494,
      "volume_ratio": null,
      "ma5": null,
      "ma20": null,
      "ma60": null,
      "cloud_pos": null,
      "aligned": null
    },
    {
      "code": "036810",
      "name": "에프에스티",
      "market": "KOSDAQ",
      "close": 43200,
      "change": 9.37,
      "cloud_top": 39550,
      "cloud_bot": 38491,
      "volume": 359312,
      "market_cap": 9264,
      "volume_ratio": null,
      "ma5": null,
      "ma20": null,
      "ma60": null,
      "cloud_pos": null,
      "aligned": null
    },
    {
      "code": "441270",
      "name": "파인엠텍",
      "market": "KOSDAQ",
      "close": 10230,
      "change": 3.54,
      "cloud_top": 9820,
      "cloud_bot": 9467,
      "volume": 341435,
      "market_cap": 4255,
      "volume_ratio": null,
      "ma5": null,
      "ma20": null,
      "ma60": null,
      "cloud_pos": null,
      "aligned": null
    },
    {
      "code": "006805",
      "name": "미래에셋증권우",
      "market": "KOSPI",
      "close": 22750,
      "change": 8.08,
      "cloud_top": 22514,
      "cloud_bot": 19962,
      "volume": 339234,
      "market_cap": 3202,
      "volume_ratio": null,
      "ma5": null,
      "ma20": null,
      "ma60": null,
      "cloud_pos": null,
      "aligned": null
    },
    {
      "code": "095190",
      "name": "이엠코리아",
      "market": "KOSDAQ",
      "close": 2490,
      "change": 3.32,
      "cloud_top": 2482,
      "cloud_bot": 2457,
      "volume": 335387,
      "market_cap": 1624,
      "volume_ratio": null,
      "ma5": null,
      "ma20": null,
      "ma60": null,
      "cloud_pos": null,
      "aligned": null
    },
    {
      "code": "051370",
      "name": "인터플렉스",
      "market": "KOSDAQ",
      "close": 12200,
      "change": 4.18,
      "cloud_top": 11792,
      "cloud_bot": 11520,
      "volume": 333180,
      "market_cap": 2845,
      "volume_ratio": null,
      "ma5": null,
      "ma20": null,
      "ma60": null,
      "cloud_pos": null,
      "aligned": null
    },
    {
      "code": "090150",
      "name": "아이윈",
      "market": "KOSDAQ",
      "close": 822,
      "change": 4.58,
      "cloud_top": 811,
      "cloud_bot": 787,
      "volume": 319979,
      "market_cap": 344,
      "volume_ratio": null,
      "ma5": null,
      "ma20": null,
      "ma60": null,
      "cloud_pos": null,
      "aligned": null
    },
    {
      "code": "060150",
      "name": "인선이엔티",
      "market": "KOSDAQ",
      "close": 4410,
      "change": 3.89,
      "cloud_top": 4255,
      "cloud_bot": 4235,
      "volume": 314464,
      "market_cap": 2053,
      "volume_ratio": null,
      "ma5": null,
      "ma20": null,
      "ma60": null,
      "cloud_pos": null,
      "aligned": null
    },
    {
      "code": "094170",
      "name": "동운아나텍",
      "market": "KOSDAQ",
      "close": 30400,
      "change": 6.29,
      "cloud_top": 29175,
      "cloud_bot": 27975,
      "volume": 298556,
      "market_cap": 6356,
      "volume_ratio": null,
      "ma5": null,
      "ma20": null,
      "ma60": null,
      "cloud_pos": null,
      "aligned": null
    },
    {
      "code": "105840",
      "name": "우진",
      "market": "KOSPI",
      "close": 23700,
      "change": 2.38,
      "cloud_top": 23625,
      "cloud_bot": 23400,
      "volume": 295684,
      "market_cap": 4786,
      "volume_ratio": null,
      "ma5": null,
      "ma20": null,
      "ma60": null,
      "cloud_pos": null,
      "aligned": null
    },
    {
      "code": "047920",
      "name": "HLB제약",
      "market": "KOSDAQ",
      "close": 18740,
      "change": 4.46,
      "cloud_top": 18000,
      "cloud_bot": 16777,
      "volume": 286455,
      "market_cap": 6146,
      "volume_ratio": null,
      "ma5": null,
      "ma20": null,
      "ma60": null,
      "cloud_pos": null,
      "aligned": null
    },
    {
      "code": "019770",
      "name": "서연탑메탈",
      "market": "KOSDAQ",
      "close": 4205,
      "change": 3.96,
      "cloud_top": 4057,
      "cloud_bot": 3895,
      "volume": 273327,
      "market_cap": 489,
      "volume_ratio": null,
      "ma5": null,
      "ma20": null,
      "ma60": null,
      "cloud_pos": null,
      "aligned": null
    },
    {
      "code": "153490",
      "name": "우리이앤엘",
      "market": "KOSDAQ",
      "close": 781,
      "change": 1.56,
      "cloud_top": 777,
      "cloud_bot": 760,
      "volume": 256245,
      "market_cap": 402,
      "volume_ratio": null,
      "ma5": null,
      "ma20": null,
      "ma60": null,
      "cloud_pos": null,
      "aligned": null
    },
    {
      "code": "294870",
      "name": "IPARK현대산업개발",
      "market": "KOSPI",
      "close": 22500,
      "change": 3.21,
      "cloud_top": 22422,
      "cloud_bot": 22320,
      "volume": 255069,
      "market_cap": 14829,
      "volume_ratio": null,
      "ma5": null,
      "ma20": null,
      "ma60": null,
      "cloud_pos": null,
      "aligned": null
    },
    {
      "code": "110990",
      "name": "디아이티",
      "market": "KOSDAQ",
      "close": 22000,
      "change": 7.06,
      "cloud_top": 21637,
      "cloud_bot": 19205,
      "volume": 242654,
      "market_cap": 4158,
      "volume_ratio": null,
      "ma5": null,
      "ma20": null,
      "ma60": null,
      "cloud_pos": null,
      "aligned": null
    },
    {
      "code": "003850",
      "name": "보령",
      "market": "KOSPI",
      "close": 10000,
      "change": 4.49,
      "cloud_top": 9710,
      "cloud_bot": 9655,
      "volume": 233584,
      "market_cap": 8578,
      "volume_ratio": null,
      "ma5": null,
      "ma20": null,
      "ma60": null,
      "cloud_pos": null,
      "aligned": null
    },
    {
      "code": "021240",
      "name": "코웨이",
      "market": "KOSPI",
      "close": 81400,
      "change": 1.88,
      "cloud_top": 79900,
      "cloud_bot": 78950,
      "volume": 231692,
      "market_cap": 57604,
      "volume_ratio": null,
      "ma5": null,
      "ma20": null,
      "ma60": null,
      "cloud_pos": null,
      "aligned": null
    },
    {
      "code": "067010",
      "name": "이씨에스",
      "market": "KOSDAQ",
      "close": 2410,
      "change": 7.59,
      "cloud_top": 2322,
      "cloud_bot": 2311,
      "volume": 230673,
      "market_cap": 262,
      "volume_ratio": null,
      "ma5": null,
      "ma20": null,
      "ma60": null,
      "cloud_pos": null,
      "aligned": null
    },
    {
      "code": "004150",
      "name": "한솔홀딩스",
      "market": "KOSPI",
      "close": 3455,
      "change": 0.88,
      "cloud_top": 3405,
      "cloud_bot": 3372,
      "volume": 222625,
      "market_cap": 1417,
      "volume_ratio": null,
      "ma5": null,
      "ma20": null,
      "ma60": null,
      "cloud_pos": null,
      "aligned": null
    },
    {
      "code": "366030",
      "name": "공구우먼",
      "market": "KOSDAQ",
      "close": 5950,
      "change": 5.68,
      "cloud_top": 5852,
      "cloud_bot": 5752,
      "volume": 212984,
      "market_cap": 1347,
      "volume_ratio": null,
      "ma5": null,
      "ma20": null,
      "ma60": null,
      "cloud_pos": null,
      "aligned": null
    },
    {
      "code": "109610",
      "name": "에스와이",
      "market": "KOSDAQ",
      "close": 2925,
      "change": 2.27,
      "cloud_top": 2852,
      "cloud_bot": 2827,
      "volume": 204929,
      "market_cap": 1430,
      "volume_ratio": null,
      "ma5": null,
      "ma20": null,
      "ma60": null,
      "cloud_pos": null,
      "aligned": null
    },
    {
      "code": "045100",
      "name": "한양이엔지",
      "market": "KOSDAQ",
      "close": 33000,
      "change": 6.28,
      "cloud_top": 31675,
      "cloud_bot": 29100,
      "volume": 203820,
      "market_cap": 5775,
      "volume_ratio": null,
      "ma5": null,
      "ma20": null,
      "ma60": null,
      "cloud_pos": null,
      "aligned": null
    },
    {
      "code": "056700",
      "name": "신화인터텍",
      "market": "KOSDAQ",
      "close": 1932,
      "change": 3.98,
      "cloud_top": 1862,
      "cloud_bot": 1844,
      "volume": 186403,
      "market_cap": 562,
      "volume_ratio": null,
      "ma5": null,
      "ma20": null,
      "ma60": null,
      "cloud_pos": null,
      "aligned": null
    },
    {
      "code": "214270",
      "name": "FSN",
      "market": "KOSDAQ",
      "close": 2135,
      "change": 2.4,
      "cloud_top": 2102,
      "cloud_bot": 2025,
      "volume": 183585,
      "market_cap": 955,
      "volume_ratio": null,
      "ma5": null,
      "ma20": null,
      "ma60": null,
      "cloud_pos": null,
      "aligned": null
    },
    {
      "code": "187420",
      "name": "HLB제넥스",
      "market": "KOSDAQ",
      "close": 2880,
      "change": 1.77,
      "cloud_top": 2855,
      "cloud_bot": 2703,
      "volume": 176126,
      "market_cap": 846,
      "volume_ratio": null,
      "ma5": null,
      "ma20": null,
      "ma60": null,
      "cloud_pos": null,
      "aligned": null
    },
    {
      "code": "017890",
      "name": "한국알콜",
      "market": "KOSDAQ",
      "close": 12130,
      "change": 3.32,
      "cloud_top": 11892,
      "cloud_bot": 11515,
      "volume": 163384,
      "market_cap": 2580,
      "volume_ratio": null,
      "ma5": null,
      "ma20": null,
      "ma60": null,
      "cloud_pos": null,
      "aligned": null
    },
    {
      "code": "264660",
      "name": "씨앤지하이테크",
      "market": "KOSDAQ",
      "close": 18740,
      "change": 3.48,
      "cloud_top": 18550,
      "cloud_bot": 18105,
      "volume": 162192,
      "market_cap": 1821,
      "volume_ratio": null,
      "ma5": null,
      "ma20": null,
      "ma60": null,
      "cloud_pos": null,
      "aligned": null
    },
    {
      "code": "033240",
      "name": "자화전자",
      "market": "KOSPI",
      "close": 35350,
      "change": 3.97,
      "cloud_top": 35100,
      "cloud_bot": 33225,
      "volume": 152375,
      "market_cap": 7637,
      "volume_ratio": null,
      "ma5": null,
      "ma20": null,
      "ma60": null,
      "cloud_pos": null,
      "aligned": null
    },
    {
      "code": "095570",
      "name": "AJ네트웍스",
      "market": "KOSPI",
      "close": 5130,
      "change": 1.18,
      "cloud_top": 5038,
      "cloud_bot": 5020,
      "volume": 149695,
      "market_cap": 2321,
      "volume_ratio": null,
      "ma5": null,
      "ma20": null,
      "ma60": null,
      "cloud_pos": null,
      "aligned": null
    },
    {
      "code": "051600",
      "name": "한전KPS",
      "market": "KOSPI",
      "close": 58400,
      "change": 2.1,
      "cloud_top": 57675,
      "cloud_bot": 57350,
      "volume": 146074,
      "market_cap": 26280,
      "volume_ratio": null,
      "ma5": null,
      "ma20": null,
      "ma60": null,
      "cloud_pos": null,
      "aligned": null
    },
    {
      "code": "084370",
      "name": "유진테크",
      "market": "KOSDAQ",
      "close": 127000,
      "change": 2.5,
      "cloud_top": 125550,
      "cloud_bot": 111600,
      "volume": 145114,
      "market_cap": 29103,
      "volume_ratio": null,
      "ma5": null,
      "ma20": null,
      "ma60": null,
      "cloud_pos": null,
      "aligned": null
    },
    {
      "code": "005945",
      "name": "NH투자증권우",
      "market": "KOSPI",
      "close": 26600,
      "change": 5.98,
      "cloud_top": 25237,
      "cloud_bot": 25055,
      "volume": 144156,
      "market_cap": 5019,
      "volume_ratio": null,
      "ma5": null,
      "ma20": null,
      "ma60": null,
      "cloud_pos": null,
      "aligned": null
    },
    {
      "code": "037560",
      "name": "LG헬로비전",
      "market": "KOSPI",
      "close": 2365,
      "change": 1.28,
      "cloud_top": 2350,
      "cloud_bot": 2350,
      "volume": 142222,
      "market_cap": 1831,
      "volume_ratio": null,
      "ma5": null,
      "ma20": null,
      "ma60": null,
      "cloud_pos": null,
      "aligned": null
    },
    {
      "code": "010960",
      "name": "삼호개발",
      "market": "KOSPI",
      "close": 4125,
      "change": 4.56,
      "cloud_top": 3991,
      "cloud_bot": 3917,
      "volume": 130740,
      "market_cap": 994,
      "volume_ratio": null,
      "ma5": null,
      "ma20": null,
      "ma60": null,
      "cloud_pos": null,
      "aligned": null
    },
    {
      "code": "330730",
      "name": "스톤브릿지벤처스",
      "market": "KOSDAQ",
      "close": 6140,
      "change": 4.42,
      "cloud_top": 6050,
      "cloud_bot": 5955,
      "volume": 128018,
      "market_cap": 1118,
      "volume_ratio": null,
      "ma5": null,
      "ma20": null,
      "ma60": null,
      "cloud_pos": null,
      "aligned": null
    },
    {
      "code": "039010",
      "name": "현대에이치티",
      "market": "KOSDAQ",
      "close": 9300,
      "change": 4.03,
      "cloud_top": 9175,
      "cloud_bot": 8970,
      "volume": 124150,
      "market_cap": 802,
      "volume_ratio": null,
      "ma5": null,
      "ma20": null,
      "ma60": null,
      "cloud_pos": null,
      "aligned": null
    },
    {
      "code": "115180",
      "name": "큐리언트",
      "market": "KOSDAQ",
      "close": 35850,
      "change": 4.52,
      "cloud_top": 34325,
      "cloud_bot": 33650,
      "volume": 120359,
      "market_cap": 13351,
      "volume_ratio": null,
      "ma5": null,
      "ma20": null,
      "ma60": null,
      "cloud_pos": null,
      "aligned": null
    },
    {
      "code": "104830",
      "name": "원익머트리얼즈",
      "market": "KOSDAQ",
      "close": 44850,
      "change": 5.9,
      "cloud_top": 43862,
      "cloud_bot": 39375,
      "volume": 104887,
      "market_cap": 5654,
      "volume_ratio": null,
      "ma5": null,
      "ma20": null,
      "ma60": null,
      "cloud_pos": null,
      "aligned": null
    },
    {
      "code": "083420",
      "name": "그린케미칼",
      "market": "KOSPI",
      "close": 6000,
      "change": 0.67,
      "cloud_top": 5990,
      "cloud_bot": 5810,
      "volume": 101674,
      "market_cap": 1440,
      "volume_ratio": null,
      "ma5": null,
      "ma20": null,
      "ma60": null,
      "cloud_pos": null,
      "aligned": null
    },
    {
      "code": "444530",
      "name": "심플랫폼",
      "market": "KOSDAQ",
      "close": 7930,
      "change": 16.45,
      "cloud_top": 6975,
      "cloud_bot": 6397,
      "volume": 98399,
      "market_cap": 507,
      "volume_ratio": null,
      "ma5": null,
      "ma20": null,
      "ma60": null,
      "cloud_pos": null,
      "aligned": null
    },
    {
      "code": "045340",
      "name": "토탈소프트",
      "market": "KOSDAQ",
      "close": 7180,
      "change": 2.43,
      "cloud_top": 7052,
      "cloud_bot": 6970,
      "volume": 98393,
      "market_cap": 614,
      "volume_ratio": null,
      "ma5": null,
      "ma20": null,
      "ma60": null,
      "cloud_pos": null,
      "aligned": null
    },
    {
      "code": "308430",
      "name": "셀비온",
      "market": "KOSDAQ",
      "close": 33100,
      "change": 4.42,
      "cloud_top": 32625,
      "cloud_bot": 31600,
      "volume": 96527,
      "market_cap": 4247,
      "volume_ratio": null,
      "ma5": null,
      "ma20": null,
      "ma60": null,
      "cloud_pos": null,
      "aligned": null
    },
    {
      "code": "014790",
      "name": "HL D&I",
      "market": "KOSPI",
      "close": 3470,
      "change": 1.17,
      "cloud_top": 3465,
      "cloud_bot": 3310,
      "volume": 82568,
      "market_cap": 1313,
      "volume_ratio": null,
      "ma5": null,
      "ma20": null,
      "ma60": null,
      "cloud_pos": null,
      "aligned": null
    },
    {
      "code": "419120",
      "name": "산돌",
      "market": "KOSDAQ",
      "close": 4160,
      "change": 2.84,
      "cloud_top": 4147,
      "cloud_bot": 4035,
      "volume": 74010,
      "market_cap": 612,
      "volume_ratio": null,
      "ma5": null,
      "ma20": null,
      "ma60": null,
      "cloud_pos": null,
      "aligned": null
    },
    {
      "code": "040610",
      "name": "SG&G",
      "market": "KOSDAQ",
      "close": 2110,
      "change": 1.44,
      "cloud_top": 2101,
      "cloud_bot": 2093,
      "volume": 71598,
      "market_cap": 719,
      "volume_ratio": null,
      "ma5": null,
      "ma20": null,
      "ma60": null,
      "cloud_pos": null,
      "aligned": null
    },
    {
      "code": "137310",
      "name": "에스디바이오센서",
      "market": "KOSPI",
      "close": 8280,
      "change": 0.85,
      "cloud_top": 8245,
      "cloud_bot": 8245,
      "volume": 66395,
      "market_cap": 10080,
      "volume_ratio": null,
      "ma5": null,
      "ma20": null,
      "ma60": null,
      "cloud_pos": null,
      "aligned": null
    },
    {
      "code": "036630",
      "name": "세종텔레콤",
      "market": "KOSDAQ",
      "close": 11600,
      "change": 4.5,
      "cloud_top": 11125,
      "cloud_bot": 8002,
      "volume": 63349,
      "market_cap": 1160,
      "volume_ratio": null,
      "ma5": null,
      "ma20": null,
      "ma60": null,
      "cloud_pos": null,
      "aligned": null
    },
    {
      "code": "051360",
      "name": "토비스",
      "market": "KOSDAQ",
      "close": 15520,
      "change": 1.84,
      "cloud_top": 15140,
      "cloud_bot": 15122,
      "volume": 55919,
      "market_cap": 2315,
      "volume_ratio": null,
      "ma5": null,
      "ma20": null,
      "ma60": null,
      "cloud_pos": null,
      "aligned": null
    },
    {
      "code": "005720",
      "name": "넥센",
      "market": "KOSPI",
      "close": 6980,
      "change": 5.12,
      "cloud_top": 6947,
      "cloud_bot": 6770,
      "volume": 54721,
      "market_cap": 3737,
      "volume_ratio": null,
      "ma5": null,
      "ma20": null,
      "ma60": null,
      "cloud_pos": null,
      "aligned": null
    },
    {
      "code": "155650",
      "name": "와이엠씨",
      "market": "KOSDAQ",
      "close": 3795,
      "change": 2.02,
      "cloud_top": 3790,
      "cloud_bot": 3790,
      "volume": 52855,
      "market_cap": 720,
      "volume_ratio": null,
      "ma5": null,
      "ma20": null,
      "ma60": null,
      "cloud_pos": null,
      "aligned": null
    },
    {
      "code": "075130",
      "name": "플랜티넷",
      "market": "KOSDAQ",
      "close": 2340,
      "change": 2.86,
      "cloud_top": 2300,
      "cloud_bot": 2226,
      "volume": 48800,
      "market_cap": 388,
      "volume_ratio": null,
      "ma5": null,
      "ma20": null,
      "ma60": null,
      "cloud_pos": null,
      "aligned": null
    },
    {
      "code": "000670",
      "name": "영풍",
      "market": "KOSPI",
      "close": 62700,
      "change": 5.73,
      "cloud_top": 59400,
      "cloud_bot": 56775,
      "volume": 45170,
      "market_cap": 11334,
      "volume_ratio": null,
      "ma5": null,
      "ma20": null,
      "ma60": null,
      "cloud_pos": null,
      "aligned": null
    },
    {
      "code": "093380",
      "name": "풍강",
      "market": "KOSDAQ",
      "close": 2760,
      "change": 1.66,
      "cloud_top": 2697,
      "cloud_bot": 2697,
      "volume": 44106,
      "market_cap": 272,
      "volume_ratio": null,
      "ma5": null,
      "ma20": null,
      "ma60": null,
      "cloud_pos": null,
      "aligned": null
    },
    {
      "code": "000500",
      "name": "가온전선",
      "market": "KOSPI",
      "close": 106000,
      "change": 3.62,
      "cloud_top": 104900,
      "cloud_bot": 102400,
      "volume": 41004,
      "market_cap": 17535,
      "volume_ratio": null,
      "ma5": null,
      "ma20": null,
      "ma60": null,
      "cloud_pos": null,
      "aligned": null
    },
    {
      "code": "036560",
      "name": "KZ정밀",
      "market": "KOSDAQ",
      "close": 14970,
      "change": 2.11,
      "cloud_top": 14415,
      "cloud_bot": 13635,
      "volume": 40678,
      "market_cap": 2357,
      "volume_ratio": null,
      "ma5": null,
      "ma20": null,
      "ma60": null,
      "cloud_pos": null,
      "aligned": null
    },
    {
      "code": "063570",
      "name": "NICE인프라",
      "market": "KOSDAQ",
      "close": 4210,
      "change": 2.18,
      "cloud_top": 4137,
      "cloud_bot": 4128,
      "volume": 34114,
      "market_cap": 1437,
      "volume_ratio": null,
      "ma5": null,
      "ma20": null,
      "ma60": null,
      "cloud_pos": null,
      "aligned": null
    },
    {
      "code": "078340",
      "name": "컴투스",
      "market": "KOSDAQ",
      "close": 33900,
      "change": 1.8,
      "cloud_top": 33750,
      "cloud_bot": 33687,
      "volume": 33969,
      "market_cap": 4098,
      "volume_ratio": null,
      "ma5": null,
      "ma20": null,
      "ma60": null,
      "cloud_pos": null,
      "aligned": null
    },
    {
      "code": "131220",
      "name": "대한과학",
      "market": "KOSDAQ",
      "close": 4620,
      "change": 2.21,
      "cloud_top": 4540,
      "cloud_bot": 4540,
      "volume": 33902,
      "market_cap": 344,
      "volume_ratio": null,
      "ma5": null,
      "ma20": null,
      "ma60": null,
      "cloud_pos": null,
      "aligned": null
    },
    {
      "code": "424980",
      "name": "마이크로투나노",
      "market": "KOSDAQ",
      "close": 13390,
      "change": 7.12,
      "cloud_top": 13307,
      "cloud_bot": 11945,
      "volume": 32822,
      "market_cap": 792,
      "volume_ratio": null,
      "ma5": null,
      "ma20": null,
      "ma60": null,
      "cloud_pos": null,
      "aligned": null
    },
    {
      "code": "344820",
      "name": "KCC글라스",
      "market": "KOSPI",
      "close": 28300,
      "change": 2.54,
      "cloud_top": 28275,
      "cloud_bot": 28225,
      "volume": 32099,
      "market_cap": 4519,
      "volume_ratio": null,
      "ma5": null,
      "ma20": null,
      "ma60": null,
      "cloud_pos": null,
      "aligned": null
    },
    {
      "code": "318000",
      "name": "KBG",
      "market": "KOSDAQ",
      "close": 4330,
      "change": 1.64,
      "cloud_top": 4260,
      "cloud_bot": 4192,
      "volume": 30032,
      "market_cap": 378,
      "volume_ratio": null,
      "ma5": null,
      "ma20": null,
      "ma60": null,
      "cloud_pos": null,
      "aligned": null
    },
    {
      "code": "025540",
      "name": "한국단자",
      "market": "KOSPI",
      "close": 75100,
      "change": 1.49,
      "cloud_top": 74850,
      "cloud_bot": 74700,
      "volume": 27983,
      "market_cap": 7596,
      "volume_ratio": null,
      "ma5": null,
      "ma20": null,
      "ma60": null,
      "cloud_pos": null,
      "aligned": null
    },
    {
      "code": "101530",
      "name": "해태제과식품",
      "market": "KOSPI",
      "close": 6770,
      "change": 1.5,
      "cloud_top": 6725,
      "cloud_bot": 6680,
      "volume": 27127,
      "market_cap": 1971,
      "volume_ratio": null,
      "ma5": null,
      "ma20": null,
      "ma60": null,
      "cloud_pos": null,
      "aligned": null
    },
    {
      "code": "136540",
      "name": "윈스테크넷",
      "market": "KOSDAQ",
      "close": 11580,
      "change": 1.31,
      "cloud_top": 11450,
      "cloud_bot": 11330,
      "volume": 23790,
      "market_cap": 1421,
      "volume_ratio": null,
      "ma5": null,
      "ma20": null,
      "ma60": null,
      "cloud_pos": null,
      "aligned": null
    },
    {
      "code": "000155",
      "name": "두산우",
      "market": "KOSPI",
      "close": 557000,
      "change": 5.89,
      "cloud_top": 529000,
      "cloud_bot": 525000,
      "volume": 19258,
      "market_cap": 22260,
      "volume_ratio": null,
      "ma5": null,
      "ma20": null,
      "ma60": null,
      "cloud_pos": null,
      "aligned": null
    },
    {
      "code": "408920",
      "name": "메쎄이상",
      "market": "KOSDAQ",
      "close": 3510,
      "change": 0.86,
      "cloud_top": 3502,
      "cloud_bot": 3358,
      "volume": 17687,
      "market_cap": 1517,
      "volume_ratio": null,
      "ma5": null,
      "ma20": null,
      "ma60": null,
      "cloud_pos": null,
      "aligned": null
    },
    {
      "code": "236200",
      "name": "슈프리마",
      "market": "KOSDAQ",
      "close": 47050,
      "change": 2.62,
      "cloud_top": 46725,
      "cloud_bot": 43200,
      "volume": 16924,
      "market_cap": 3281,
      "volume_ratio": null,
      "ma5": null,
      "ma20": null,
      "ma60": null,
      "cloud_pos": null,
      "aligned": null
    },
    {
      "code": "025530",
      "name": "SJM홀딩스",
      "market": "KOSPI",
      "close": 3700,
      "change": 1.65,
      "cloud_top": 3677,
      "cloud_bot": 3653,
      "volume": 14264,
      "market_cap": 552,
      "volume_ratio": null,
      "ma5": null,
      "ma20": null,
      "ma60": null,
      "cloud_pos": null,
      "aligned": null
    },
    {
      "code": "037710",
      "name": "광주신세계",
      "market": "KOSPI",
      "close": 37250,
      "change": 1.78,
      "cloud_top": 36800,
      "cloud_bot": 35600,
      "volume": 12697,
      "market_cap": 2964,
      "volume_ratio": null,
      "ma5": null,
      "ma20": null,
      "ma60": null,
      "cloud_pos": null,
      "aligned": null
    },
    {
      "code": "134380",
      "name": "미원화학",
      "market": "KOSPI",
      "close": 11250,
      "change": 2.27,
      "cloud_top": 10940,
      "cloud_bot": 10830,
      "volume": 9935,
      "market_cap": 2474,
      "volume_ratio": null,
      "ma5": null,
      "ma20": null,
      "ma60": null,
      "cloud_pos": null,
      "aligned": null
    },
    {
      "code": "016670",
      "name": "디모아",
      "market": "KOSDAQ",
      "close": 4300,
      "change": 1.53,
      "cloud_top": 4290,
      "cloud_bot": 4290,
      "volume": 9653,
      "market_cap": 438,
      "volume_ratio": null,
      "ma5": null,
      "ma20": null,
      "ma60": null,
      "cloud_pos": null,
      "aligned": null
    },
    {
      "code": "467930",
      "name": "IBKS제23호스팩",
      "market": "KOSDAQ",
      "close": 2240,
      "change": 1.13,
      "cloud_top": 2237,
      "cloud_bot": 2227,
      "volume": 4494,
      "market_cap": 94,
      "volume_ratio": null,
      "ma5": null,
      "ma20": null,
      "ma60": null,
      "cloud_pos": null,
      "aligned": null
    },
    {
      "code": "002170",
      "name": "삼양통상",
      "market": "KOSPI",
      "close": 59400,
      "change": 1.89,
      "cloud_top": 58800,
      "cloud_bot": 57600,
      "volume": 2487,
      "market_cap": 1782,
      "volume_ratio": null,
      "ma5": null,
      "ma20": null,
      "ma60": null,
      "cloud_pos": null,
      "aligned": null
    },
    {
      "code": "058650",
      "name": "세아홀딩스",
      "market": "KOSPI",
      "close": 155000,
      "change": 0.91,
      "cloud_top": 154200,
      "cloud_bot": 153050,
      "volume": 1378,
      "market_cap": 6685,
      "volume_ratio": null,
      "ma5": null,
      "ma20": null,
      "ma60": null,
      "cloud_pos": null,
      "aligned": null
    },
    {
      "code": "393970",
      "name": "대진첨단소재",
      "market": "KOSDAQ",
      "close": 2825,
      "change": 0.0,
      "cloud_top": 2640,
      "cloud_bot": 2190,
      "volume": 0,
      "market_cap": 504,
      "volume_ratio": null,
      "ma5": null,
      "ma20": null,
      "ma60": null,
      "cloud_pos": null,
      "aligned": null
    }
  ],
  "sell": [
    {
      "code": "005860",
      "name": "한일사료",
      "market": "KOSDAQ",
      "close": 4070,
      "change": -4.24,
      "cloud_top": 4170,
      "cloud_bot": 4117,
      "volume": 2405448,
      "market_cap": 1603,
      "volume_ratio": null,
      "ma5": null,
      "ma20": null,
      "ma60": null,
      "cloud_pos": null,
      "aligned": null
    },
    {
      "code": "900250",
      "name": "크리스탈신소재",
      "market": "KOSDAQ",
      "close": 575,
      "change": -5.74,
      "cloud_top": 623,
      "cloud_bot": 605,
      "volume": 1705777,
      "market_cap": 823,
      "volume_ratio": null,
      "ma5": null,
      "ma20": null,
      "ma60": null,
      "cloud_pos": null,
      "aligned": null
    },
    {
      "code": "294630",
      "name": "서남",
      "market": "KOSDAQ",
      "close": 4255,
      "change": -6.89,
      "cloud_top": 4320,
      "cloud_bot": 4275,
      "volume": 1484003,
      "market_cap": 1121,
      "volume_ratio": null,
      "ma5": null,
      "ma20": null,
      "ma60": null,
      "cloud_pos": null,
      "aligned": null
    },
    {
      "code": "029480",
      "name": "광무",
      "market": "KOSDAQ",
      "close": 2275,
      "change": -5.21,
      "cloud_top": 2475,
      "cloud_bot": 2325,
      "volume": 918970,
      "market_cap": 1358,
      "volume_ratio": null,
      "ma5": null,
      "ma20": null,
      "ma60": null,
      "cloud_pos": null,
      "aligned": null
    },
    {
      "code": "458870",
      "name": "씨어스테크놀로지",
      "market": "KOSDAQ",
      "close": 43250,
      "change": -9.04,
      "cloud_top": 47475,
      "cloud_bot": 45565,
      "volume": 592403,
      "market_cap": 16460,
      "volume_ratio": null,
      "ma5": null,
      "ma20": null,
      "ma60": null,
      "cloud_pos": null,
      "aligned": null
    },
    {
      "code": "141080",
      "name": "리가켐바이오",
      "market": "KOSDAQ",
      "close": 181000,
      "change": -4.13,
      "cloud_top": 187575,
      "cloud_bot": 181550,
      "volume": 536857,
      "market_cap": 66264,
      "volume_ratio": null,
      "ma5": null,
      "ma20": null,
      "ma60": null,
      "cloud_pos": null,
      "aligned": null
    },
    {
      "code": "175330",
      "name": "JB금융지주",
      "market": "KOSPI",
      "close": 30600,
      "change": -1.77,
      "cloud_top": 31225,
      "cloud_bot": 30775,
      "volume": 433325,
      "market_cap": 57605,
      "volume_ratio": null,
      "ma5": null,
      "ma20": null,
      "ma60": null,
      "cloud_pos": null,
      "aligned": null
    },
    {
      "code": "246710",
      "name": "티앤알바이오팹",
      "market": "KOSDAQ",
      "close": 3250,
      "change": -1.22,
      "cloud_top": 3812,
      "cloud_bot": 3273,
      "volume": 430158,
      "market_cap": 1545,
      "volume_ratio": null,
      "ma5": null,
      "ma20": null,
      "ma60": null,
      "cloud_pos": null,
      "aligned": null
    },
    {
      "code": "001040",
      "name": "CJ",
      "market": "KOSPI",
      "close": 197100,
      "change": -2.91,
      "cloud_top": 200250,
      "cloud_bot": 199875,
      "volume": 199467,
      "market_cap": 57507,
      "volume_ratio": null,
      "ma5": null,
      "ma20": null,
      "ma60": null,
      "cloud_pos": null,
      "aligned": null
    },
    {
      "code": "033200",
      "name": "모아텍",
      "market": "KOSDAQ",
      "close": 4080,
      "change": -2.51,
      "cloud_top": 4157,
      "cloud_bot": 4150,
      "volume": 166286,
      "market_cap": 584,
      "volume_ratio": null,
      "ma5": null,
      "ma20": null,
      "ma60": null,
      "cloud_pos": null,
      "aligned": null
    },
    {
      "code": "002100",
      "name": "경농",
      "market": "KOSPI",
      "close": 10020,
      "change": 0.7,
      "cloud_top": 10225,
      "cloud_bot": 10225,
      "volume": 140313,
      "market_cap": 1956,
      "volume_ratio": null,
      "ma5": null,
      "ma20": null,
      "ma60": null,
      "cloud_pos": null,
      "aligned": null
    },
    {
      "code": "003670",
      "name": "포스코퓨처엠",
      "market": "KOSPI",
      "close": 213000,
      "change": -0.7,
      "cloud_top": 219250,
      "cloud_bot": 213250,
      "volume": 134605,
      "market_cap": 189455,
      "volume_ratio": null,
      "ma5": null,
      "ma20": null,
      "ma60": null,
      "cloud_pos": null,
      "aligned": null
    },
    {
      "code": "006890",
      "name": "태경케미컬",
      "market": "KOSPI",
      "close": 8790,
      "change": 0.23,
      "cloud_top": 8895,
      "cloud_bot": 8895,
      "volume": 131921,
      "market_cap": 1019,
      "volume_ratio": null,
      "ma5": null,
      "ma20": null,
      "ma60": null,
      "cloud_pos": null,
      "aligned": null
    },
    {
      "code": "011230",
      "name": "삼화전자",
      "market": "KOSPI",
      "close": 2565,
      "change": -1.35,
      "cloud_top": 2885,
      "cloud_bot": 2591,
      "volume": 105934,
      "market_cap": 491,
      "volume_ratio": null,
      "ma5": null,
      "ma20": null,
      "ma60": null,
      "cloud_pos": null,
      "aligned": null
    },
    {
      "code": "054050",
      "name": "농우바이오",
      "market": "KOSDAQ",
      "close": 8100,
      "change": 0.0,
      "cloud_top": 8220,
      "cloud_bot": 8220,
      "volume": 87734,
      "market_cap": 1298,
      "volume_ratio": null,
      "ma5": null,
      "ma20": null,
      "ma60": null,
      "cloud_pos": null,
      "aligned": null
    },
    {
      "code": "259960",
      "name": "크래프톤",
      "market": "KOSPI",
      "close": 239000,
      "change": -1.04,
      "cloud_top": 243500,
      "cloud_bot": 241000,
      "volume": 73617,
      "market_cap": 113300,
      "volume_ratio": null,
      "ma5": null,
      "ma20": null,
      "ma60": null,
      "cloud_pos": null,
      "aligned": null
    },
    {
      "code": "460470",
      "name": "아이빔테크놀로지",
      "market": "KOSDAQ",
      "close": 3470,
      "change": -1.7,
      "cloud_top": 3510,
      "cloud_bot": 3492,
      "volume": 44708,
      "market_cap": 524,
      "volume_ratio": null,
      "ma5": null,
      "ma20": null,
      "ma60": null,
      "cloud_pos": null,
      "aligned": null
    },
    {
      "code": "186230",
      "name": "그린플러스",
      "market": "KOSDAQ",
      "close": 4695,
      "change": -1.26,
      "cloud_top": 5235,
      "cloud_bot": 4745,
      "volume": 41995,
      "market_cap": 512,
      "volume_ratio": null,
      "ma5": null,
      "ma20": null,
      "ma60": null,
      "cloud_pos": null,
      "aligned": null
    },
    {
      "code": "065370",
      "name": "위세아이텍",
      "market": "KOSDAQ",
      "close": 5290,
      "change": -2.04,
      "cloud_top": 5407,
      "cloud_bot": 5300,
      "volume": 26624,
      "market_cap": 390,
      "volume_ratio": null,
      "ma5": null,
      "ma20": null,
      "ma60": null,
      "cloud_pos": null,
      "aligned": null
    },
    {
      "code": "010130",
      "name": "고려아연",
      "market": "KOSPI",
      "close": 1649000,
      "change": -0.84,
      "cloud_top": 1873500,
      "cloud_bot": 1659500,
      "volume": 21545,
      "market_cap": 344195,
      "volume_ratio": null,
      "ma5": null,
      "ma20": null,
      "ma60": null,
      "cloud_pos": null,
      "aligned": null
    },
    {
      "code": "002820",
      "name": "SUN&L",
      "market": "KOSPI",
      "close": 2310,
      "change": -2.12,
      "cloud_top": 2487,
      "cloud_bot": 2313,
      "volume": 10869,
      "market_cap": 291,
      "volume_ratio": null,
      "ma5": null,
      "ma20": null,
      "ma60": null,
      "cloud_pos": null,
      "aligned": null
    },
    {
      "code": "109860",
      "name": "동일금속",
      "market": "KOSDAQ",
      "close": 7340,
      "change": -1.08,
      "cloud_top": 7570,
      "cloud_bot": 7355,
      "volume": 7551,
      "market_cap": 667,
      "volume_ratio": null,
      "ma5": null,
      "ma20": null,
      "ma60": null,
      "cloud_pos": null,
      "aligned": null
    },
    {
      "code": "493790",
      "name": "유안타제17호스팩",
      "market": "KOSDAQ",
      "close": 2005,
      "change": -0.5,
      "cloud_top": 2018,
      "cloud_bot": 2014,
      "volume": 1677,
      "market_cap": 106,
      "volume_ratio": null,
      "ma5": null,
      "ma20": null,
      "ma60": null,
      "cloud_pos": null,
      "aligned": null
    },
    {
      "code": "475250",
      "name": "하나33호스팩",
      "market": "KOSDAQ",
      "close": 2095,
      "change": -0.24,
      "cloud_top": 2103,
      "cloud_bot": 2100,
      "volume": 7,
      "market_cap": 77,
      "volume_ratio": null,
      "ma5": null,
      "ma20": null,
      "ma60": null,
      "cloud_pos": null,
      "aligned": null
    }
  ],
  "entry": [
    {
      "code": "900100",
      "name": "애머릿지",
      "market": "KOSDAQ",
      "close": 608,
      "change": 10.95,
      "cloud_top": 596,
      "cloud_bot": 468,
      "volume": 22174416,
      "market_cap": 320,
      "volume_ratio": 15.0,
      "ma5": 431.0,
      "ma20": 397.0,
      "ma60": 463.0,
      "cloud_pos": "구름 위",
      "aligned": false
    },
    {
      "code": "227950",
      "name": "엔투텍",
      "market": "KOSDAQ",
      "close": 542,
      "change": 19.12,
      "cloud_top": 561,
      "cloud_bot": 536,
      "volume": 13738508,
      "market_cap": 935,
      "volume_ratio": 6.9,
      "ma5": 460.0,
      "ma20": 444.0,
      "ma60": 430.0,
      "cloud_pos": "구름 안",
      "aligned": true
    },
    {
      "code": "003310",
      "name": "대주산업",
      "market": "KOSDAQ",
      "close": 4035,
      "change": 7.03,
      "cloud_top": 4366,
      "cloud_bot": 4135,
      "volume": 11756216,
      "market_cap": 1428,
      "volume_ratio": 5.9,
      "ma5": 3739.0,
      "ma20": 3646.0,
      "ma60": 4040.0,
      "cloud_pos": "구름 아래",
      "aligned": false
    },
    {
      "code": "006920",
      "name": "모헨즈",
      "market": "KOSDAQ",
      "close": 5770,
      "change": 15.17,
      "cloud_top": 5023,
      "cloud_bot": 4890,
      "volume": 6695385,
      "market_cap": 630,
      "volume_ratio": 4.6,
      "ma5": 5226.0,
      "ma20": 5030.0,
      "ma60": 4394.0,
      "cloud_pos": "구름 위",
      "aligned": true
    },
    {
      "code": "347000",
      "name": "센코",
      "market": "KOSDAQ",
      "close": 2330,
      "change": 8.12,
      "cloud_top": 2295,
      "cloud_bot": 2253,
      "volume": 5600614,
      "market_cap": 880,
      "volume_ratio": 14.5,
      "ma5": 2192.0,
      "ma20": 2180.0,
      "ma60": 2213.0,
      "cloud_pos": "구름 위",
      "aligned": false
    },
    {
      "code": "434480",
      "name": "모니터랩",
      "market": "KOSDAQ",
      "close": 3970,
      "change": 17.11,
      "cloud_top": 3755,
      "cloud_bot": 3618,
      "volume": 4707781,
      "market_cap": 488,
      "volume_ratio": 17.8,
      "ma5": 3487.0,
      "ma20": 3445.0,
      "ma60": 3635.0,
      "cloud_pos": "구름 위",
      "aligned": false
    },
    {
      "code": "048430",
      "name": "유라테크",
      "market": "KOSDAQ",
      "close": 8950,
      "change": 16.54,
      "cloud_top": 7935,
      "cloud_bot": 7912,
      "volume": 3538943,
      "market_cap": 1031,
      "volume_ratio": 18.4,
      "ma5": 7860.0,
      "ma20": 7598.0,
      "ma60": 7940.0,
      "cloud_pos": "구름 위",
      "aligned": false
    },
    {
      "code": "052900",
      "name": "KX하이텍",
      "market": "KOSDAQ",
      "close": 1271,
      "change": 9.95,
      "cloud_top": 1258,
      "cloud_bot": 1238,
      "volume": 3513185,
      "market_cap": 883,
      "volume_ratio": 4.1,
      "ma5": 1166.0,
      "ma20": 1133.0,
      "ma60": 1161.0,
      "cloud_pos": "구름 위",
      "aligned": false
    },
    {
      "code": "102120",
      "name": "어보브반도체",
      "market": "KOSDAQ",
      "close": 12160,
      "change": 8.96,
      "cloud_top": 12095,
      "cloud_bot": 12095,
      "volume": 3470004,
      "market_cap": 2162,
      "volume_ratio": 9.7,
      "ma5": 11338.0,
      "ma20": 11184.0,
      "ma60": 11784.0,
      "cloud_pos": "구름 위",
      "aligned": false
    },
    {
      "code": "085670",
      "name": "뉴프렉스",
      "market": "KOSDAQ",
      "close": 6240,
      "change": 12.64,
      "cloud_top": 5835,
      "cloud_bot": 5717,
      "volume": 3230452,
      "market_cap": 1525,
      "volume_ratio": 6.6,
      "ma5": 5622.0,
      "ma20": 5507.0,
      "ma60": 5860.0,
      "cloud_pos": "구름 위",
      "aligned": false
    },
    {
      "code": "043260",
      "name": "성호전자",
      "market": "KOSDAQ",
      "close": 53200,
      "change": 10.83,
      "cloud_top": 28550,
      "cloud_bot": 22475,
      "volume": 3006366,
      "market_cap": 37730,
      "volume_ratio": 2.2,
      "ma5": 45870.0,
      "ma20": 44265.0,
      "ma60": 31658.0,
      "cloud_pos": "구름 위",
      "aligned": true
    },
    {
      "code": "241520",
      "name": "DSC인베스트먼트",
      "market": "KOSDAQ",
      "close": 14950,
      "change": 7.48,
      "cloud_top": 15022,
      "cloud_bot": 13320,
      "volume": 2994321,
      "market_cap": 4036,
      "volume_ratio": 2.7,
      "ma5": 14002.0,
      "ma20": 13777.0,
      "ma60": 12608.0,
      "cloud_pos": "구름 안",
      "aligned": true
    },
    {
      "code": "078890",
      "name": "가온그룹",
      "market": "KOSDAQ",
      "close": 7850,
      "change": 29.97,
      "cloud_top": 6830,
      "cloud_bot": 6340,
      "volume": 2734194,
      "market_cap": 1446,
      "volume_ratio": 6.0,
      "ma5": 6206.0,
      "ma20": 6070.0,
      "ma60": 6312.0,
      "cloud_pos": "구름 위",
      "aligned": false
    },
    {
      "code": "068330",
      "name": "일신바이오",
      "market": "KOSDAQ",
      "close": 1527,
      "change": 5.24,
      "cloud_top": 1600,
      "cloud_bot": 1570,
      "volume": 2634315,
      "market_cap": 675,
      "volume_ratio": 8.2,
      "ma5": 1448.0,
      "ma20": 1426.0,
      "ma60": 1515.0,
      "cloud_pos": "구름 아래",
      "aligned": false
    },
    {
      "code": "097870",
      "name": "효성오앤비",
      "market": "KOSDAQ",
      "close": 6790,
      "change": 0.89,
      "cloud_top": 6775,
      "cloud_bot": 6775,
      "volume": 2489351,
      "market_cap": 576,
      "volume_ratio": 6.2,
      "ma5": 6376.0,
      "ma20": 6326.0,
      "ma60": 6174.0,
      "cloud_pos": "구름 위",
      "aligned": true
    },
    {
      "code": "293580",
      "name": "나우IB",
      "market": "KOSDAQ",
      "close": 1899,
      "change": 5.32,
      "cloud_top": 1985,
      "cloud_bot": 1902,
      "volume": 2244190,
      "market_cap": 1802,
      "volume_ratio": 2.8,
      "ma5": 1795.0,
      "ma20": 1762.0,
      "ma60": 1814.0,
      "cloud_pos": "구름 아래",
      "aligned": false
    },
    {
      "code": "080580",
      "name": "오킨스전자",
      "market": "KOSDAQ",
      "close": 23250,
      "change": 20.53,
      "cloud_top": 14867,
      "cloud_bot": 13720,
      "volume": 2149718,
      "market_cap": 4785,
      "volume_ratio": 2.8,
      "ma5": 20708.0,
      "ma20": 19873.0,
      "ma60": 16494.0,
      "cloud_pos": "구름 위",
      "aligned": true
    },
    {
      "code": "041190",
      "name": "우리기술투자",
      "market": "KOSDAQ",
      "close": 6690,
      "change": 6.36,
      "cloud_top": 7450,
      "cloud_bot": 7345,
      "volume": 1953884,
      "market_cap": 5619,
      "volume_ratio": 2.3,
      "ma5": 6476.0,
      "ma20": 6444.0,
      "ma60": 7220.0,
      "cloud_pos": "구름 아래",
      "aligned": false
    },
    {
      "code": "274090",
      "name": "켄코아에어로스페이스",
      "market": "KOSDAQ",
      "close": 23900,
      "change": 11.16,
      "cloud_top": 22122,
      "cloud_bot": 20870,
      "volume": 1731720,
      "market_cap": 3279,
      "volume_ratio": 2.8,
      "ma5": 21022.0,
      "ma20": 20986.0,
      "ma60": 22714.0,
      "cloud_pos": "구름 위",
      "aligned": false
    },
    {
      "code": "158430",
      "name": "아톤",
      "market": "KOSDAQ",
      "close": 6790,
      "change": 8.64,
      "cloud_top": 7035,
      "cloud_bot": 6855,
      "volume": 1446926,
      "market_cap": 1662,
      "volume_ratio": 4.8,
      "ma5": 6304.0,
      "ma20": 6228.0,
      "ma60": 6766.0,
      "cloud_pos": "구름 아래",
      "aligned": false
    },
    {
      "code": "380550",
      "name": "뉴로핏",
      "market": "KOSDAQ",
      "close": 22650,
      "change": 6.59,
      "cloud_top": 28475,
      "cloud_bot": 27012,
      "volume": 1270143,
      "market_cap": 2738,
      "volume_ratio": 2.5,
      "ma5": 20794.0,
      "ma20": 20626.0,
      "ma60": 24279.0,
      "cloud_pos": "구름 아래",
      "aligned": false
    },
    {
      "code": "306040",
      "name": "에스제이그룹",
      "market": "KOSDAQ",
      "close": 8080,
      "change": 9.19,
      "cloud_top": 10570,
      "cloud_bot": 10540,
      "volume": 1213874,
      "market_cap": 797,
      "volume_ratio": 2.9,
      "ma5": 7090.0,
      "ma20": 6900.0,
      "ma60": 9270.0,
      "cloud_pos": "구름 아래",
      "aligned": false
    },
    {
      "code": "066980",
      "name": "한성크린텍",
      "market": "KOSDAQ",
      "close": 1559,
      "change": 8.72,
      "cloud_top": 1391,
      "cloud_bot": 1391,
      "volume": 1014716,
      "market_cap": 809,
      "volume_ratio": 2.1,
      "ma5": 1462.0,
      "ma20": 1417.0,
      "ma60": 1329.0,
      "cloud_pos": "구름 위",
      "aligned": true
    },
    {
      "code": "021080",
      "name": "에이티넘인베스트",
      "market": "KOSDAQ",
      "close": 3265,
      "change": 7.76,
      "cloud_top": 3335,
      "cloud_bot": 3295,
      "volume": 977531,
      "market_cap": 1567,
      "volume_ratio": 2.7,
      "ma5": 3057.0,
      "ma20": 2995.0,
      "ma60": 3133.0,
      "cloud_pos": "구름 아래",
      "aligned": false
    },
    {
      "code": "036200",
      "name": "유니셈",
      "market": "KOSDAQ",
      "close": 10600,
      "change": 8.05,
      "cloud_top": 10285,
      "cloud_bot": 10122,
      "volume": 927081,
      "market_cap": 3250,
      "volume_ratio": 3.9,
      "ma5": 9694.0,
      "ma20": 9474.0,
      "ma60": 9984.0,
      "cloud_pos": "구름 위",
      "aligned": false
    },
    {
      "code": "232830",
      "name": "아이티센피엔에스",
      "market": "KOSDAQ",
      "close": 3475,
      "change": 16.61,
      "cloud_top": 2290,
      "cloud_bot": 2197,
      "volume": 877367,
      "market_cap": 574,
      "volume_ratio": 6.3,
      "ma5": 2905.0,
      "ma20": 2770.0,
      "ma60": 2437.0,
      "cloud_pos": "구름 위",
      "aligned": true
    },
    {
      "code": "355390",
      "name": "크라우드웍스",
      "market": "KOSDAQ",
      "close": 3300,
      "change": 29.92,
      "cloud_top": 3612,
      "cloud_bot": 2960,
      "volume": 867216,
      "market_cap": 514,
      "volume_ratio": 7.5,
      "ma5": 2605.0,
      "ma20": 2589.0,
      "ma60": 3002.0,
      "cloud_pos": "구름 안",
      "aligned": false
    },
    {
      "code": "044380",
      "name": "주연테크",
      "market": "KOSPI",
      "close": 422,
      "change": 5.5,
      "cloud_top": 377,
      "cloud_bot": 377,
      "volume": 740044,
      "market_cap": 272,
      "volume_ratio": 4.0,
      "ma5": 385.0,
      "ma20": 376.0,
      "ma60": 382.0,
      "cloud_pos": "구름 위",
      "aligned": false
    },
    {
      "code": "430690",
      "name": "한싹",
      "market": "KOSDAQ",
      "close": 4690,
      "change": 29.92,
      "cloud_top": 4220,
      "cloud_bot": 3947,
      "volume": 726262,
      "market_cap": 510,
      "volume_ratio": 11.4,
      "ma5": 3782.0,
      "ma20": 3695.0,
      "ma60": 4069.0,
      "cloud_pos": "구름 위",
      "aligned": false
    },
    {
      "code": "004985",
      "name": "성신양회우",
      "market": "KOSPI",
      "close": 13740,
      "change": 27.93,
      "cloud_top": 12450,
      "cloud_bot": 11052,
      "volume": 632760,
      "market_cap": 101,
      "volume_ratio": 18.3,
      "ma5": 11374.0,
      "ma20": 10940.0,
      "ma60": 11152.0,
      "cloud_pos": "구름 위",
      "aligned": false
    },
    {
      "code": "272110",
      "name": "케이엔제이",
      "market": "KOSDAQ",
      "close": 40300,
      "change": 14.16,
      "cloud_top": 31150,
      "cloud_bot": 29225,
      "volume": 502123,
      "market_cap": 3234,
      "volume_ratio": 3.4,
      "ma5": 35690.0,
      "ma20": 34822.0,
      "ma60": 31917.0,
      "cloud_pos": "구름 위",
      "aligned": true
    },
    {
      "code": "092300",
      "name": "현우산업",
      "market": "KOSDAQ",
      "close": 3390,
      "change": 8.13,
      "cloud_top": 3350,
      "cloud_bot": 3350,
      "volume": 448417,
      "market_cap": 645,
      "volume_ratio": 5.0,
      "ma5": 3171.0,
      "ma20": 3128.0,
      "ma60": 3308.0,
      "cloud_pos": "구름 위",
      "aligned": false
    },
    {
      "code": "032620",
      "name": "GC메디아이",
      "market": "KOSDAQ",
      "close": 4195,
      "change": 2.82,
      "cloud_top": 4005,
      "cloud_bot": 3978,
      "volume": 429425,
      "market_cap": 2189,
      "volume_ratio": 2.2,
      "ma5": 4015.0,
      "ma20": 3987.0,
      "ma60": 3989.0,
      "cloud_pos": "구름 위",
      "aligned": false
    },
    {
      "code": "000680",
      "name": "LS네트웍스",
      "market": "KOSPI",
      "close": 3250,
      "change": 1.88,
      "cloud_top": 3300,
      "cloud_bot": 3300,
      "volume": 398387,
      "market_cap": 2561,
      "volume_ratio": 2.8,
      "ma5": 3186.0,
      "ma20": 3157.0,
      "ma60": 3326.0,
      "cloud_pos": "구름 아래",
      "aligned": false
    },
    {
      "code": "037400",
      "name": "우리엔터프라이즈",
      "market": "KOSDAQ",
      "close": 1019,
      "change": 3.45,
      "cloud_top": 1051,
      "cloud_bot": 1000,
      "volume": 354006,
      "market_cap": 267,
      "volume_ratio": 4.6,
      "ma5": 984.0,
      "ma20": 982.0,
      "ma60": 962.0,
      "cloud_pos": "구름 안",
      "aligned": true
    },
    {
      "code": "006805",
      "name": "미래에셋증권우",
      "market": "KOSPI",
      "close": 22750,
      "change": 8.08,
      "cloud_top": 22514,
      "cloud_bot": 19962,
      "volume": 339234,
      "market_cap": 3202,
      "volume_ratio": 2.3,
      "ma5": 21700.0,
      "ma20": 21680.0,
      "ma60": 20873.0,
      "cloud_pos": "구름 위",
      "aligned": true
    },
    {
      "code": "014440",
      "name": "영보화학",
      "market": "KOSPI",
      "close": 4790,
      "change": 3.57,
      "cloud_top": 4942,
      "cloud_bot": 4767,
      "volume": 298348,
      "market_cap": 958,
      "volume_ratio": 6.1,
      "ma5": 4643.0,
      "ma20": 4639.0,
      "ma60": 4707.0,
      "cloud_pos": "구름 안",
      "aligned": false
    },
    {
      "code": "019170",
      "name": "신풍제약",
      "market": "KOSPI",
      "close": 10920,
      "change": -1.62,
      "cloud_top": 12335,
      "cloud_bot": 11490,
      "volume": 275310,
      "market_cap": 5724,
      "volume_ratio": 2.6,
      "ma5": 10676.0,
      "ma20": 10672.0,
      "ma60": 11695.0,
      "cloud_pos": "구름 아래",
      "aligned": false
    },
    {
      "code": "002800",
      "name": "신신제약",
      "market": "KOSDAQ",
      "close": 5840,
      "change": 5.23,
      "cloud_top": 6070,
      "cloud_bot": 5722,
      "volume": 248319,
      "market_cap": 885,
      "volume_ratio": 4.1,
      "ma5": 5590.0,
      "ma20": 5524.0,
      "ma60": 5700.0,
      "cloud_pos": "구름 안",
      "aligned": false
    },
    {
      "code": "058860",
      "name": "KTis",
      "market": "KOSPI",
      "close": 2885,
      "change": 2.67,
      "cloud_top": 2922,
      "cloud_bot": 2905,
      "volume": 234188,
      "market_cap": 1004,
      "volume_ratio": 2.1,
      "ma5": 2812.0,
      "ma20": 2799.0,
      "ma60": 2828.0,
      "cloud_pos": "구름 아래",
      "aligned": false
    },
    {
      "code": "419530",
      "name": "SAMG엔터",
      "market": "KOSDAQ",
      "close": 36600,
      "change": 9.91,
      "cloud_top": 39550,
      "cloud_bot": 36250,
      "volume": 229433,
      "market_cap": 3657,
      "volume_ratio": 3.8,
      "ma5": 34010.0,
      "ma20": 33530.0,
      "ma60": 35547.0,
      "cloud_pos": "구름 안",
      "aligned": false
    },
    {
      "code": "083310",
      "name": "엘오티베큠",
      "market": "KOSDAQ",
      "close": 13860,
      "change": 4.21,
      "cloud_top": 13030,
      "cloud_bot": 12957,
      "volume": 222973,
      "market_cap": 2468,
      "volume_ratio": 2.0,
      "ma5": 13156.0,
      "ma20": 12996.0,
      "ma60": 13088.0,
      "cloud_pos": "구름 위",
      "aligned": false
    },
    {
      "code": "056700",
      "name": "신화인터텍",
      "market": "KOSDAQ",
      "close": 1932,
      "change": 3.98,
      "cloud_top": 1862,
      "cloud_bot": 1844,
      "volume": 186403,
      "market_cap": 562,
      "volume_ratio": 3.6,
      "ma5": 1838.0,
      "ma20": 1830.0,
      "ma60": 1826.0,
      "cloud_pos": "구름 위",
      "aligned": true
    },
    {
      "code": "094360",
      "name": "칩스앤미디어",
      "market": "KOSDAQ",
      "close": 17200,
      "change": 5.72,
      "cloud_top": 17825,
      "cloud_bot": 17400,
      "volume": 185605,
      "market_cap": 3669,
      "volume_ratio": 2.5,
      "ma5": 16286.0,
      "ma20": 16239.0,
      "ma60": 17355.0,
      "cloud_pos": "구름 아래",
      "aligned": false
    },
    {
      "code": "140070",
      "name": "서플러스글로벌",
      "market": "KOSDAQ",
      "close": 2120,
      "change": 4.43,
      "cloud_top": 1998,
      "cloud_bot": 1985,
      "volume": 180864,
      "market_cap": 784,
      "volume_ratio": 2.7,
      "ma5": 1972.0,
      "ma20": 1934.0,
      "ma60": 2010.0,
      "cloud_pos": "구름 위",
      "aligned": false
    },
    {
      "code": "190510",
      "name": "나무가",
      "market": "KOSDAQ",
      "close": 18230,
      "change": 6.67,
      "cloud_top": 22655,
      "cloud_bot": 21440,
      "volume": 180371,
      "market_cap": 2567,
      "volume_ratio": 3.0,
      "ma5": 17384.0,
      "ma20": 17307.0,
      "ma60": 20914.0,
      "cloud_pos": "구름 아래",
      "aligned": false
    },
    {
      "code": "094940",
      "name": "푸른기술",
      "market": "KOSDAQ",
      "close": 9800,
      "change": 3.27,
      "cloud_top": 11640,
      "cloud_bot": 10015,
      "volume": 173138,
      "market_cap": 819,
      "volume_ratio": 2.1,
      "ma5": 9590.0,
      "ma20": 9532.0,
      "ma60": 10324.0,
      "cloud_pos": "구름 아래",
      "aligned": false
    },
    {
      "code": "088340",
      "name": "유라클",
      "market": "KOSDAQ",
      "close": 12300,
      "change": 5.58,
      "cloud_top": 13485,
      "cloud_bot": 12750,
      "volume": 166311,
      "market_cap": 536,
      "volume_ratio": 5.6,
      "ma5": 11762.0,
      "ma20": 11714.0,
      "ma60": 12944.0,
      "cloud_pos": "구름 아래",
      "aligned": false
    },
    {
      "code": "054450",
      "name": "텔레칩스",
      "market": "KOSDAQ",
      "close": 13100,
      "change": 4.38,
      "cloud_top": 14065,
      "cloud_bot": 13452,
      "volume": 161358,
      "market_cap": 1983,
      "volume_ratio": 2.1,
      "ma5": 12574.0,
      "ma20": 12486.0,
      "ma60": 13826.0,
      "cloud_pos": "구름 아래",
      "aligned": false
    },
    {
      "code": "050860",
      "name": "아세아텍",
      "market": "KOSDAQ",
      "close": 1998,
      "change": 0.05,
      "cloud_top": 2019,
      "cloud_bot": 1997,
      "volume": 137009,
      "market_cap": 449,
      "volume_ratio": 3.4,
      "ma5": 1995.0,
      "ma20": 1993.0,
      "ma60": 1981.0,
      "cloud_pos": "구름 안",
      "aligned": true
    },
    {
      "code": "407400",
      "name": "꿈비",
      "market": "KOSDAQ",
      "close": 4330,
      "change": 4.72,
      "cloud_top": 4810,
      "cloud_bot": 4510,
      "volume": 136980,
      "market_cap": 633,
      "volume_ratio": 2.5,
      "ma5": 4128.0,
      "ma20": 4076.0,
      "ma60": 4478.0,
      "cloud_pos": "구름 아래",
      "aligned": false
    },
    {
      "code": "092460",
      "name": "한라IMS",
      "market": "KOSDAQ",
      "close": 16370,
      "change": 6.3,
      "cloud_top": 16675,
      "cloud_bot": 14842,
      "volume": 130106,
      "market_cap": 2800,
      "volume_ratio": 2.4,
      "ma5": 15590.0,
      "ma20": 15386.0,
      "ma60": 15654.0,
      "cloud_pos": "구름 안",
      "aligned": false
    },
    {
      "code": "338220",
      "name": "뷰노",
      "market": "KOSDAQ",
      "close": 18190,
      "change": 5.63,
      "cloud_top": 20225,
      "cloud_bot": 18350,
      "volume": 125644,
      "market_cap": 2546,
      "volume_ratio": 2.5,
      "ma5": 16718.0,
      "ma20": 16426.0,
      "ma60": 18421.0,
      "cloud_pos": "구름 아래",
      "aligned": false
    },
    {
      "code": "445090",
      "name": "에이직랜드",
      "market": "KOSDAQ",
      "close": 28600,
      "change": 5.93,
      "cloud_top": 29000,
      "cloud_bot": 28575,
      "volume": 114197,
      "market_cap": 3124,
      "volume_ratio": 2.3,
      "ma5": 27720.0,
      "ma20": 27545.0,
      "ma60": 29348.0,
      "cloud_pos": "구름 안",
      "aligned": false
    },
    {
      "code": "187270",
      "name": "신화콘텍",
      "market": "KOSDAQ",
      "close": 3745,
      "change": 4.76,
      "cloud_top": 3780,
      "cloud_bot": 3686,
      "volume": 97968,
      "market_cap": 379,
      "volume_ratio": 2.0,
      "ma5": 3575.0,
      "ma20": 3552.0,
      "ma60": 3614.0,
      "cloud_pos": "구름 안",
      "aligned": false
    },
    {
      "code": "029460",
      "name": "케이씨",
      "market": "KOSPI",
      "close": 35700,
      "change": 8.35,
      "cloud_top": 31700,
      "cloud_bot": 29850,
      "volume": 93709,
      "market_cap": 4594,
      "volume_ratio": 2.2,
      "ma5": 32320.0,
      "ma20": 31545.0,
      "ma60": 31478.0,
      "cloud_pos": "구름 위",
      "aligned": true
    },
    {
      "code": "417860",
      "name": "오브젠",
      "market": "KOSDAQ",
      "close": 9710,
      "change": -2.9,
      "cloud_top": 10240,
      "cloud_bot": 9137,
      "volume": 91138,
      "market_cap": 456,
      "volume_ratio": 2.4,
      "ma5": 9010.0,
      "ma20": 8788.0,
      "ma60": 9510.0,
      "cloud_pos": "구름 안",
      "aligned": false
    },
    {
      "code": "318160",
      "name": "셀바이오휴먼텍",
      "market": "KOSDAQ",
      "close": 7260,
      "change": 0.97,
      "cloud_top": 7780,
      "cloud_bot": 7455,
      "volume": 80694,
      "market_cap": 678,
      "volume_ratio": 2.2,
      "ma5": 7046.0,
      "ma20": 7025.0,
      "ma60": 7513.0,
      "cloud_pos": "구름 아래",
      "aligned": false
    },
    {
      "code": "402030",
      "name": "코난테크놀로지",
      "market": "KOSDAQ",
      "close": 19650,
      "change": 5.02,
      "cloud_top": 20250,
      "cloud_bot": 19537,
      "volume": 43686,
      "market_cap": 2459,
      "volume_ratio": 2.0,
      "ma5": 18508.0,
      "ma20": 18412.0,
      "ma60": 20327.0,
      "cloud_pos": "구름 안",
      "aligned": false
    },
    {
      "code": "094280",
      "name": "효성ITX",
      "market": "KOSPI",
      "close": 12550,
      "change": 1.21,
      "cloud_top": 12285,
      "cloud_bot": 12227,
      "volume": 36890,
      "market_cap": 1450,
      "volume_ratio": 2.7,
      "ma5": 12416.0,
      "ma20": 12381.0,
      "ma60": 12496.0,
      "cloud_pos": "구름 위",
      "aligned": false
    },
    {
      "code": "084695",
      "name": "대상홀딩스우",
      "market": "KOSPI",
      "close": 14710,
      "change": -0.68,
      "cloud_top": 14925,
      "cloud_bot": 14255,
      "volume": 18135,
      "market_cap": 134,
      "volume_ratio": 2.6,
      "ma5": 14480.0,
      "ma20": 14354.0,
      "ma60": 14160.0,
      "cloud_pos": "구름 안",
      "aligned": true
    },
    {
      "code": "357550",
      "name": "석경에이티",
      "market": "KOSDAQ",
      "close": 54600,
      "change": 3.8,
      "cloud_top": 62400,
      "cloud_bot": 61800,
      "volume": 16578,
      "market_cap": 2978,
      "volume_ratio": 2.3,
      "ma5": 52160.0,
      "ma20": 51910.0,
      "ma60": 55528.0,
      "cloud_pos": "구름 아래",
      "aligned": false
    }
  ]
}